sentry_46elks/__init__.py
sentry_46elks/plugin.py
sentry_46elks-0.1.4.dist-info/DESCRIPTION.rst
sentry_46elks-0.1.4.dist-info/METADATA
sentry_46elks-0.1.4.dist-info/RECORD
sentry_46elks-0.1.4.dist-info/WHEEL
sentry_46elks-0.1.4.dist-info/entry_points.txt
sentry_46elks-0.1.4.dist-info/metadata.json
sentry_46elks-0.1.4.dist-info/top_level.txt
