Metadata-Version: 2.0
Name: sentry-46elks
Version: 0.1.4
Summary: Sentry plugin for notifying users by text through the 46elks API
Home-page: https://github.com/jmagnusson/sentry-46elks
Author: Jacob Magnusson
Author-email: m@jacobian.se
License: New BSD License
Platform: any
Classifier: Development Status :: 3 - Alpha
Classifier: Environment :: Web Environment
Classifier: Framework :: Django
Classifier: Intended Audience :: Developers
Classifier: License :: OSI Approved :: BSD License
Classifier: Operating System :: OS Independent
Classifier: Programming Language :: Python
Requires-Dist: requests (>=1.0)
